CHANGES.txt
LICENSE.txt
MANIFEST.in
README.txt
TODO.txt
buildout.cfg
setup.py
eggs/BTrees-6.1-py3.10-win-amd64.egg/EGG-INFO/LICENSE.txt
eggs/BTrees-6.1-py3.10-win-amd64.egg/EGG-INFO/requires.txt
eggs/BTrees-6.1-py3.10-win-amd64.egg/EGG-INFO/top_level.txt
eggs/Paste-3.10.1-py3.10.egg/EGG-INFO/entry_points.txt
eggs/Paste-3.10.1-py3.10.egg/EGG-INFO/namespace_packages.txt
eggs/Paste-3.10.1-py3.10.egg/EGG-INFO/requires.txt
eggs/Paste-3.10.1-py3.10.egg/EGG-INFO/top_level.txt
eggs/PasteDeploy-3.1.0-py3.10.egg/EGG-INFO/entry_points.txt
eggs/PasteDeploy-3.1.0-py3.10.egg/EGG-INFO/namespace_packages.txt
eggs/PasteDeploy-3.1.0-py3.10.egg/EGG-INFO/requires.txt
eggs/PasteDeploy-3.1.0-py3.10.egg/EGG-INFO/top_level.txt
eggs/PasteScript-3.7.0-py3.10.egg/EGG-INFO/entry_points.txt
eggs/PasteScript-3.7.0-py3.10.egg/EGG-INFO/namespace_packages.txt
eggs/PasteScript-3.7.0-py3.10.egg/EGG-INFO/requires.txt
eggs/PasteScript-3.7.0-py3.10.egg/EGG-INFO/top_level.txt
eggs/ZConfig-4.2-py3.10.egg/EGG-INFO/LICENSE.txt
eggs/ZConfig-4.2-py3.10.egg/EGG-INFO/entry_points.txt
eggs/ZConfig-4.2-py3.10.egg/EGG-INFO/requires.txt
eggs/ZConfig-4.2-py3.10.egg/EGG-INFO/top_level.txt
eggs/ZConfig-4.2-py3.10.egg/ZConfig/schemaless.txt
eggs/ZConfig-4.2-py3.10.egg/ZConfig/tests/input/non-ascii.txt
eggs/ZConfig-4.2-py3.10.egg/ZConfig/tests/library/README.txt
eggs/ZConfig-4.2-py3.10.egg/ZConfig/tests/zipsource/README.txt
eggs/ZEO-6.0.0-py3.10.egg/EGG-INFO/LICENSE.txt
eggs/ZEO-6.0.0-py3.10.egg/EGG-INFO/entry_points.txt
eggs/ZEO-6.0.0-py3.10.egg/EGG-INFO/requires.txt
eggs/ZEO-6.0.0-py3.10.egg/EGG-INFO/top_level.txt
eggs/ZEO-6.0.0-py3.10.egg/ZEO/version.txt
eggs/ZEO-6.0.0-py3.10.egg/ZEO/scripts/README.txt
eggs/ZEO-6.0.0-py3.10.egg/ZEO/tests/drop_cache_rather_than_verify.txt
eggs/ZEO-6.0.0-py3.10.egg/ZEO/tests/invalidation-age.txt
eggs/cffi-1.17.1-py3.10-win-amd64.egg/EGG-INFO/entry_points.txt
eggs/cffi-1.17.1-py3.10-win-amd64.egg/EGG-INFO/requires.txt
eggs/cffi-1.17.1-py3.10-win-amd64.egg/EGG-INFO/top_level.txt
eggs/importlib_metadata-8.7.0-py3.10.egg/EGG-INFO/requires.txt
eggs/importlib_metadata-8.7.0-py3.10.egg/EGG-INFO/top_level.txt
eggs/lxml-6.0.0-py3.10-win-amd64.egg/EGG-INFO/requires.txt
eggs/lxml-6.0.0-py3.10-win-amd64.egg/EGG-INFO/top_level.txt
eggs/lxml-6.0.0-py3.10-win-amd64.egg/EGG-INFO/licenses/LICENSE.txt
eggs/lxml-6.0.0-py3.10-win-amd64.egg/EGG-INFO/licenses/LICENSES.txt
eggs/lxml-6.0.0-py3.10-win-amd64.egg/lxml/isoschematron/resources/xsl/iso-schematron-xslt1/readme.txt
eggs/multipart-0.1.1-py3.10.egg/EGG-INFO/top_level.txt
eggs/multipart-1.2.1-py3.10.egg/EGG-INFO/requires.txt
eggs/p01.checker-0.5.9-py3.10.egg/EGG-INFO/SOURCES.txt
eggs/p01.checker-0.5.9-py3.10.egg/EGG-INFO/dependency_links.txt
eggs/p01.checker-0.5.9-py3.10.egg/EGG-INFO/namespace_packages.txt
eggs/p01.checker-0.5.9-py3.10.egg/EGG-INFO/requires.txt
eggs/p01.checker-0.5.9-py3.10.egg/EGG-INFO/top_level.txt
eggs/p01.checker-0.5.9-py3.10.egg/p01/checker/checker.txt
eggs/p01.checker-0.5.9-py3.10.egg/p01/checker/sample/tab.txt
eggs/persistent-6.1.1-py3.10-win-amd64.egg/EGG-INFO/LICENSE.txt
eggs/persistent-6.1.1-py3.10-win-amd64.egg/EGG-INFO/requires.txt
eggs/persistent-6.1.1-py3.10-win-amd64.egg/EGG-INFO/top_level.txt
eggs/polib-1.2.0-py3.10.egg/EGG-INFO/top_level.txt
eggs/pycparser-2.22-py3.10.egg/EGG-INFO/top_level.txt
eggs/pyflakes-3.4.0-py3.10.egg/EGG-INFO/entry_points.txt
eggs/pyflakes-3.4.0-py3.10.egg/EGG-INFO/top_level.txt
eggs/python_gettext-5.0-py3.10.egg/EGG-INFO/top_level.txt
eggs/pytz-2025.2-py3.10.egg/EGG-INFO/LICENSE.txt
eggs/pytz-2025.2-py3.10.egg/EGG-INFO/top_level.txt
eggs/six-1.17.0-py3.10.egg/EGG-INFO/top_level.txt
eggs/transaction-5.0-py3.10.egg/EGG-INFO/LICENSE.txt
eggs/transaction-5.0-py3.10.egg/EGG-INFO/requires.txt
eggs/transaction-5.0-py3.10.egg/EGG-INFO/top_level.txt
eggs/zc.lockfile-3.0.post1-py3.10.egg/EGG-INFO/LICENSE.txt
eggs/zc.lockfile-3.0.post1-py3.10.egg/EGG-INFO/namespace_packages.txt
eggs/zc.lockfile-3.0.post1-py3.10.egg/EGG-INFO/requires.txt
eggs/zc.lockfile-3.0.post1-py3.10.egg/EGG-INFO/top_level.txt
eggs/zc.lockfile-3.0.post1-py3.10.egg/zc/lockfile/README.txt
eggs/zc.recipe.egg-2.0.7-py3.10.egg/EGG-INFO/SOURCES.txt
eggs/zc.recipe.egg-2.0.7-py3.10.egg/EGG-INFO/dependency_links.txt
eggs/zc.recipe.egg-2.0.7-py3.10.egg/EGG-INFO/entry_points.txt
eggs/zc.recipe.egg-2.0.7-py3.10.egg/EGG-INFO/namespace_packages.txt
eggs/zc.recipe.egg-2.0.7-py3.10.egg/EGG-INFO/requires.txt
eggs/zc.recipe.egg-2.0.7-py3.10.egg/EGG-INFO/top_level.txt
eggs/zc.recipe.testrunner-2.0.0-py3.10.egg/EGG-INFO/SOURCES.txt
eggs/zc.recipe.testrunner-2.0.0-py3.10.egg/EGG-INFO/dependency_links.txt
eggs/zc.recipe.testrunner-2.0.0-py3.10.egg/EGG-INFO/entry_points.txt
eggs/zc.recipe.testrunner-2.0.0-py3.10.egg/EGG-INFO/namespace_packages.txt
eggs/zc.recipe.testrunner-2.0.0-py3.10.egg/EGG-INFO/requires.txt
eggs/zc.recipe.testrunner-2.0.0-py3.10.egg/EGG-INFO/top_level.txt
eggs/zc.recipe.testrunner-2.0.0-py3.10.egg/zc/recipe/testrunner/README.txt
eggs/zc.recipe.testrunner-2.0.0-py3.10.egg/zc/recipe/testrunner/bugfixes.txt
eggs/zdaemon-5.2-py3.10.egg/EGG-INFO/LICENSE.txt
eggs/zdaemon-5.2-py3.10.egg/EGG-INFO/entry_points.txt
eggs/zdaemon-5.2-py3.10.egg/EGG-INFO/requires.txt
eggs/zdaemon-5.2-py3.10.egg/EGG-INFO/top_level.txt
eggs/zipp-3.23.0-py3.10.egg/EGG-INFO/requires.txt
eggs/zipp-3.23.0-py3.10.egg/EGG-INFO/top_level.txt
eggs/zodb-6.0.1-py3.10.egg/EGG-INFO/LICENSE.txt
eggs/zodb-6.0.1-py3.10.egg/EGG-INFO/entry_points.txt
eggs/zodb-6.0.1-py3.10.egg/EGG-INFO/requires.txt
eggs/zodb-6.0.1-py3.10.egg/EGG-INFO/top_level.txt
eggs/zodb-6.0.1-py3.10.egg/ZODB/FileStorage/zconfig.txt
eggs/zodb-6.0.1-py3.10.egg/ZODB/scripts/README.txt
eggs/zodb-6.0.1-py3.10.egg/ZODB/scripts/tests/fstail.txt
eggs/zodb-6.0.1-py3.10.egg/ZODB/scripts/tests/referrers.txt
eggs/zodb-6.0.1-py3.10.egg/ZODB/tests/blob_basic.txt
eggs/zodb-6.0.1-py3.10.egg/ZODB/tests/blob_connection.txt
eggs/zodb-6.0.1-py3.10.egg/ZODB/tests/blob_consume.txt
eggs/zodb-6.0.1-py3.10.egg/ZODB/tests/blob_importexport.txt
