Metadata-Version: 2.1
Name: p01.recipe.setup
Version: 0.8.21
Summary: Development and installation recipes
Home-page: http://pypi.python.org/pypi/p01.recipe.setup
Author: Roger Ineichen and the Zope Community
Author-email: zope-dev@zope.org
License: ZPL 2.1
Keywords: zope3 p01 dev recipe setup installation installer
Platform: UNKNOWN
Classifier: Development Status :: 3 - Alpha
Classifier: Environment :: Web Environment
Classifier: Intended Audience :: Developers
Classifier: License :: OSI Approved :: Zope Public License
Classifier: Programming Language :: Python
Classifier: Programming Language :: Python :: 2
Classifier: Programming Language :: Python :: 2.7
Classifier: Programming Language :: Python :: 3
Classifier: Programming Language :: Python :: 3.5
Classifier: Programming Language :: Python :: 3.6
Classifier: Programming Language :: Python :: 3.7
Classifier: Programming Language :: Python :: 3.8
Classifier: Programming Language :: Python :: 3.9
Classifier: Programming Language :: Python :: 3.10
Classifier: Programming Language :: Python :: 3.11
Classifier: Programming Language :: Python :: 3.12
Classifier: Natural Language :: English
Classifier: Operating System :: OS Independent
Classifier: Topic :: Internet :: WWW/HTTP
Classifier: Framework :: Zope3
Provides-Extra: i18n
Provides-Extra: test
Provides-Extra: paste
Provides-Extra: sphinx
